<?xml version="1.0" encoding="utf-8"?>
<!DOCTYPE hibernate-mapping PUBLIC "-//Hibernate/Hibernate Mapping DTD 3.0//EN"
"http://hibernate.sourceforge.net/hibernate-mapping-3.0.dtd">
<!-- 
    Mapping file autogenerated by MyEclipse Persistence Tools
-->
<hibernate-mapping>
    <class name="com.masi.hibernate.Xsgz" table="xsgz" catalog="masi">
        <id name="xsgzid" type="integer">
            <column name="xsgzid" />
            <generator class="assigned" />
        </id>
        <property name="xsgzname" type="string">
            <column name="xsgzname" />
        </property>
        <property name="xsgztype" type="string">
            <column name="xsgztype" />
        </property>
        <property name="xsgzattri" type="string">
            <column name="xsgzattri" />
        </property>
        <property name="xsgzaddr" type="string">
            <column name="xsgzaddr" />
        </property>
        <property name="xsgzaddrtemp" type="string">
            <column name="xsgzaddrtemp" />
        </property>
        <property name="xsgzloadtime" type="timestamp">
            <column name="xsgzloadtime" length="19" />
        </property>
        <property name="xsgzpubltime" type="timestamp">
            <column name="xsgzpubltime" length="19" />
        </property>
        <property name="xsgzkeyword" type="string">
            <column name="xsgzkeyword" />
        </property>
        <property name="xsgzreadednum" type="integer">
            <column name="xsgzreadednum" />
        </property>
        <property name="xsgzpublisher" type="string">
            <column name="xsgzpublisher" />
        </property>
        <property name="xsgzcode" type="string">
            <column name="xsgzcode" />
        </property>
    </class>
</hibernate-mapping>
